main.py
RecursiveGraphNexus/doc_generator.py
RecursiveGraphNexus/logbook_tracker.py
RecursiveGraphNexus/meta_knowledge_synth.py
RecursiveGraphNexus/openapi_handler.py
ai/character_embodiment.py
ai/echo_bridge.py
ai/execution_monitor.py
ai/failure_recovery.py
ai/memory_guard.py
ai/mode_transition_manager.py
ai/nudge_registry.py
ai/recursive_adaptation.py
ai/rerm_activation_manager.py
ai/rerm_watchdog.py
ai/semiotic_cli.py
ai/semiotic_table_engine.py
ai/speclang_cli.py
api/echo_sync/__init__.py
api/echo_sync/config.py
api/echo_sync/exceptions.py
api/echo_sync/models.py
api/echo_sync/monitoring.py
api/echo_sync/routes.py
api/echo_sync/setup_db.py
api/echo_sync/database/init_db.py
api/echo_sync/database/migrate.py
api/echo_sync/database/models.py
api/echo_sync/database/repositories.py
api/echo_sync/database/session.py
api/echo_sync/database/setup.py
api/echo_sync/database/migrations/env.py
api/echo_sync/database/migrations/versions/initial_migration.py
api/echo_sync/middleware/auth.py
api/echo_sync/services/sync_service.py
api/echo_sync/tests/__init__.py
api/echo_sync/tests/test_sync_service.py
ava8/__init__.py
ava8/cli.py
ava8/composer.py
ava8/glyph_to_tone.json
cadro/__init__.py
cadro/cadro.py
cadro/character_embodiment.py
cadro/cli.py
cadro/failure_recovery.py
cadro/run_ui.py
cadro/setup.py
cadro/ui.py
cadro/upkeyscli.py
discussion/causal_inference.py
echonexus-0.3.2.dist-info/licenses/LICENSE
ghindexer/discussion_clustering.py
ghindexer/echo_tracking.py
ghindexer/github_api_wrapper.py
ghindexer/issue_indexing.py
ghindexer/openapi_integration.py
ghindexer/real_time_prioritization.py
ghindexer/recursive_trace_logger.py
ghindexer/stagnation_scoring.py
ghindexer/webhook_handler.py
logging/recursive_trace_logger.py
rsmp/character_embodiment.py
rsmp/failure_recovery.py
rsmp/recursive_adaptation.py
saocc/__init__.py
saocc/character_embodiment.py
saocc/cli.py
saocc/core.py
saocc/failure_recovery.py
saocc/recursive_adaptation.py
setup/echo-sync_add_sample_to_redis.py
upkeys/__init__.py
upkeys/cli.py
echonexus-0.3.2.dist-info/METADATA
echonexus-0.3.2.dist-info/WHEEL
echonexus-0.3.2.dist-info/entry_points.txt
echonexus-0.3.2.dist-info/top_level.txt
echonexus-0.3.2.dist-info/RECORD
