Metadata-Version: 2.4
Name: echonexus
Version: 0.3.2
Summary: EchoNexus AI framework with Ava8 symphony
Author: EchoNexus Team
Requires-Python: >=3.10
License-File: LICENSE
Requires-Dist: click
Requires-Dist: upstash-redis
Requires-Dist: flask
Requires-Dist: numpy
Requires-Dist: pandas
Requires-Dist: matplotlib
Requires-Dist: redis
Requires-Dist: midiutil
Requires-Dist: fastapi
Requires-Dist: sqlalchemy
Requires-Dist: pydantic-settings
Requires-Dist: python-jose
Requires-Dist: prometheus-client
Provides-Extra: dev
Requires-Dist: pytest; extra == "dev"
Requires-Dist: twine; extra == "dev"
Provides-Extra: ml
Requires-Dist: sentence-transformers; extra == "ml"
Requires-Dist: faiss-cpu; extra == "ml"
Requires-Dist: scikit-learn; extra == "ml"
Requires-Dist: causalnex; extra == "ml"
Dynamic: license-file
